poetry_templating/__init__.py
poetry_templating/engine.py
poetry_templating/error.py
poetry_templating/plugin.py
poetry_templating/util.py
poetry_templating-1.1.2.dist-info/LICENCE
poetry_templating-1.1.2.dist-info/METADATA
poetry_templating-1.1.2.dist-info/WHEEL
poetry_templating-1.1.2.dist-info/entry_points.txt
poetry_templating-1.1.2.dist-info/RECORD
