Metadata-Version: 2.1
Name: poetry-templating
Version: 1.1.2
Summary: A plugin for poetry which lets you substitute text on build.
Home-page: https://github.com/NimajnebEC/poetry-templating
License: MIT
Author: NimajnebEC
Author-email: nimajnebec@users.noreply.github.com
Requires-Python: >=3.8,<3.13
Classifier: License :: OSI Approved :: MIT License
Classifier: Programming Language :: Python :: 3
Classifier: Programming Language :: Python :: 3.8
Classifier: Programming Language :: Python :: 3.9
Classifier: Programming Language :: Python :: 3.10
Classifier: Programming Language :: Python :: 3.11
Classifier: Programming Language :: Python :: 3.12
Requires-Dist: poetry (>=1.8.0,<2.0.0)
Project-URL: Repository, https://github.com/NimajnebEC/poetry-templating
